MANIFEST.in
README.md
get_alphabetagamma.c
get_log_permanent.c
header.h
help_functions.c
main_python.py
methods.c
methods_sparse.c
pyproject.toml
setup.cfg
setup.py
xxhash.c
xxhash.h
perms.egg-info/PKG-INFO
perms.egg-info/SOURCES.txt
perms.egg-info/dependency_links.txt
perms.egg-info/requires.txt
perms.egg-info/top_level.txt