Metadata-Version: 2.1
Name: perms
Version: 1.23
Summary: Marginal Likelihood estimation via Permutation counting
Author: Dennis Christensen, Per August Jarval Moen
Author-email: Dennis Christensen <dennis.christensen@ffi.no>, Per August Jarval Moen <pamoen@math.uio.no>
Project-URL: Homepage, https://github.com/peraugustmoen/perms
Classifier: Programming Language :: Python :: 3
Classifier: License :: OSI Approved :: BSD License
Classifier: Operating System :: OS Independent
Requires-Python: >=3.7
